Workbook

Sheet README
A1: Game Balance Workbook
A2: Edit yellow/current-value columns to rebalance. Formula columns recalculate in Excel.
A3: Sheets
A4: Assumptions: global knobs used by formulas.
A5: Feeds: feed XP, grow rates, and effective XP/min.
A6: Pets: pet earnings, MaxXP, feed mapping, and calculated evolution minutes.
A7: Seeds: roll rarity/chance/price plus formula price helpers.
A8: LuckUpgrades: 100-level luck curve, raw formula, current prices, cumulative cost.
A9: RollPads: roll-pad upgrade costs.
A10: Rebirths: rebirth costs and anchor formula checks.
A11: Note: RollChanceN is displayed raw in roll UI as "1 in N".

Sheet Assumptions
A1: Key | B1: Value | C1: Description
A2: SeedMinutesRequired | B2: 3 | C2: Default minutes used by seed formula price helper.
A3: TreeHarvestsPerSecond | B3: 1 | C3: Tree effective XP/min assumes this many harvested fruits per second.
A4: PatchDefaultGrowRate | B4: 1 | C4: Patches currently tick every second.
A5: EndgameIncomePerSecond | B5: 1000 | C5: Used for upgrade hour estimates.
A6: LuckRawA | B6: 35 | C6: Raw luck formula coefficient.
A7: LuckRawB | B7: 16 | C7: Raw luck formula cubic multiplier.
A8: LuckRawExponent | B8: 3.25 | C8: Raw luck formula exponent.

Sheet Feeds
A1: FeedType | B1: FeedClass | C1: XP | D1: GrowRateSeconds | E1: EffectiveXPPerMinute | F1: Notes
A2: PumpkinPatch | B2: Patch | C2: 1 | D2: 1 | E2: =IF(B2="Patch",C2*60/D2,C2*Assumptions!$B$3*60) | F2: starter patch
A3: CabbagePatch | B3: Patch | C3: 2 | D3: 1 | E3: =IF(B3="Patch",C3*60/D3,C3*Assumptions!$B$3*60) | F3: early patch
A4: AppleTree | B4: Tree | C4: 2 | E4: =IF(B4="Patch",C4*60/D4,C4*Assumptions!$B$3*60) | F4: tree fruit XP
A5: PotatoPatch | B5: Patch | C5: 3 | D5: 1 | E5: =IF(B5="Patch",C5*60/D5,C5*Assumptions!$B$3*60)
A6: OrangeTree | B6: Tree | C6: 4 | E6: =IF(B6="Patch",C6*60/D6,C6*Assumptions!$B$3*60)
A7: WatermelonPatch | B7: Patch | C7: 7 | D7: 1 | E7: =IF(B7="Patch",C7*60/D7,C7*Assumptions!$B$3*60)
A8: PlumTree | B8: Tree | C8: 12 | E8: =IF(B8="Patch",C8*60/D8,C8*Assumptions!$B$3*60)
A9: CornPatch | B9: Patch | C9: 18 | D9: 1 | E9: =IF(B9="Patch",C9*60/D9,C9*Assumptions!$B$3*60)
A10: CherryTree | B10: Tree | C10: 30 | E10: =IF(B10="Patch",C10*60/D10,C10*Assumptions!$B$3*60)
A11: MushroomPatch | B11: Patch | C11: 48 | D11: 1 | E11: =IF(B11="Patch",C11*60/D11,C11*Assumptions!$B$3*60)
A12: BananaTree | B12: Tree | C12: 80 | E12: =IF(B12="Patch",C12*60/D12,C12*Assumptions!$B$3*60)
A13: Cactus | B13: Tree | C13: 130 | E13: =IF(B13="Patch",C13*60/D13,C13*Assumptions!$B$3*60)
A14: PineapplePatch | B14: Patch | C14: 217 | D14: 1 | E14: =IF(B14="Patch",C14*60/D14,C14*Assumptions!$B$3*60)
A15: FigTree | B15: Tree | C15: 370 | E15: =IF(B15="Patch",C15*60/D15,C15*Assumptions!$B$3*60)
A16: PurpleShroomPatch | B16: Patch | C16: 633 | D16: 1 | E16: =IF(B16="Patch",C16*60/D16,C16*Assumptions!$B$3*60)
A17: BloodOrangeTree | B17: Tree | C17: 1100 | E17: =IF(B17="Patch",C17*60/D17,C17*Assumptions!$B$3*60)
A18: GlowshroomPatch | B18: Patch | C18: 1933 | D18: 1 | E18: =IF(B18="Patch",C18*60/D18,C18*Assumptions!$B$3*60)
A19: DragonfruitTree | B19: Tree | C19: 3350 | E19: =IF(B19="Patch",C19*60/D19,C19*Assumptions!$B$3*60)
A20: GoldenAppleTree | B20: Tree | C20: 5700 | E20: =IF(B20="Patch",C20*60/D20,C20*Assumptions!$B$3*60)
A21: DurianTree | B21: Tree | C21: 10000 | E21: =IF(B21="Patch",C21*60/D21,C21*Assumptions!$B$3*60)

Sheet Pets
A1: Order | B1: PetID | C1: DisplayName | D1: Rarity | E1: MoneyRatePerSecond | F1: MaxXP | G1: EvolutionFeedType | H1: FeedXPPerMinute | I1: ApproxMinutesToNext | J1: NextPetID
A2: 1 | B2: Pet1 | C2: Chicken | D2: Common | E2: 1 | F2: 40 | G2: PumpkinPatch | H2: =IF(G2="","",VLOOKUP(G2,Feeds!$A:$E,5,FALSE)) | I2: =IF(OR(F2="",H2=""),"",ROUND(F2/H2,1)) | J2: Pet2
A3: 2 | B3: Pet2 | C3: Hamster | D3: Common | E3: 2 | F3: 60 | G3: PumpkinPatch | H3: =IF(G3="","",VLOOKUP(G3,Feeds!$A:$E,5,FALSE)) | I3: =IF(OR(F3="",H3=""),"",ROUND(F3/H3,1)) | J3: Pet3
A4: 3 | B4: Pet3 | C4: GuiennaPig | D4: Common | E4: 3 | F4: 80 | G4: PumpkinPatch | H4: =IF(G4="","",VLOOKUP(G4,Feeds!$A:$E,5,FALSE)) | I4: =IF(OR(F4="",H4=""),"",ROUND(F4/H4,1)) | J4: Pet4
A5: 4 | B5: Pet4 | C5: Bunny | D5: Common | E5: 5 | F5: 150 | G5: CabbagePatch | H5: =IF(G5="","",VLOOKUP(G5,Feeds!$A:$E,5,FALSE)) | I5: =IF(OR(F5="",H5=""),"",ROUND(F5/H5,1)) | J5: Pet5
A6: 5 | B6: Pet5 | C6: Pigeon | D6: Common | E6: 6 | F6: 180 | G6: CabbagePatch | H6: =IF(G6="","",VLOOKUP(G6,Feeds!$A:$E,5,FALSE)) | I6: =IF(OR(F6="",H6=""),"",ROUND(F6/H6,1)) | J6: Pet6
A7: 6 | B7: Pet6 | C7: Parrot | D7: Common | E7: 8 | F7: 200 | G7: CabbagePatch | H7: =IF(G7="","",VLOOKUP(G7,Feeds!$A:$E,5,FALSE)) | I7: =IF(OR(F7="",H7=""),"",ROUND(F7/H7,1)) | J7: Pet7
A8: 7 | B8: Pet7 | C8: Owl | D8: Common | E8: 9 | F8: 500 | G8: AppleTree | H8: =IF(G8="","",VLOOKUP(G8,Feeds!$A:$E,5,FALSE)) | I8: =IF(OR(F8="",H8=""),"",ROUND(F8/H8,1)) | J8: Pet8
A9: 8 | B9: Pet8 | C9: Bat | D9: Common | E9: 11 | F9: 600 | G9: AppleTree | H9: =IF(G9="","",VLOOKUP(G9,Feeds!$A:$E,5,FALSE)) | I9: =IF(OR(F9="",H9=""),"",ROUND(F9/H9,1)) | J9: Pet9
A10: 9 | B10: Pet9 | C10: Cat | D10: Common | E10: 12 | F10: 850 | G10: PotatoPatch | H10: =IF(G10="","",VLOOKUP(G10,Feeds!$A:$E,5,FALSE)) | I10: =IF(OR(F10="",H10=""),"",ROUND(F10/H10,1)) | J10: Pet10
A11: 10 | B11: Pet10 | C11: Goat | D11: Common | E11: 14 | F11: 950 | G11: PotatoPatch | H11: =IF(G11="","",VLOOKUP(G11,Feeds!$A:$E,5,FALSE)) | I11: =IF(OR(F11="",H11=""),"",ROUND(F11/H11,1)) | J11: Pet11
A12: 11 | B12: Pet11 | C12: Cow | D12: Rare | E12: 15 | F12: 1200 | G12: PotatoPatch | H12: =IF(G12="","",VLOOKUP(G12,Feeds!$A:$E,5,FALSE)) | I12: =IF(OR(F12="",H12=""),"",ROUND(F12/H12,1)) | J12: Pet12
A13: 12 | B13: Pet12 | C13: Bull | D13: Rare | E13: 17 | F13: 2000 | G13: OrangeTree | H13: =IF(G13="","",VLOOKUP(G13,Feeds!$A:$E,5,FALSE)) | I13: =IF(OR(F13="",H13=""),"",ROUND(F13/H13,1)) | J13: Pet13
... A53: 52 | B53: Pet52 | C53: Kitsune | D53: Mythical | E53: 950 | F53: 1600000000 | G53: DurianTree | H53: =IF(G53="","",VLOOKUP(G53,Feeds!$A:$E,5,FALSE)) | I53: =IF(OR(F53="",H53=""),"",ROUND(F53/H53,1)) | J53: Pet53
A54: 53 | B54: Pet53 | C54: Unicorn | D54: Mythical | E54: 1000 | H54: =IF(G54="","",VLOOKUP(G54,Feeds!$A:$E,5,FALSE)) | I54: =IF(OR(F54="",H54=""),"",ROUND(F54/H54,1))

Sheet Seeds
A1: SeedID | B1: DisplayName | C1: FeedType | D1: Rarity | E1: RollChanceN | F1: RawChanceLabel | G1: MatchedPetID | H1: MatchedPetName | I1: MatchedMoneyRate | J1: MinutesRequired | K1: FormulaPrice | L1: CurrentPrice | M1: PriceDelta
A2: PumpkinSeed | B2: Pumpkin Seed | C2: PumpkinPatch | D2: Common | E2: 3 | F2: ="1 in "&E2 | G2: Pet1 | H2: =VLOOKUP(G2,Pets!$B:$E,2,FALSE) | I2: =VLOOKUP(G2,Pets!$B:$E,4,FALSE) | J2: =Assumptions!$B$2 | K2: =I2*60*J2 | L2: 100 | M2: =L2-K2
A3: CabbageSeed | B3: Cabbage Seed | C3: CabbagePatch | D3: Common | E3: 4 | F3: ="1 in "&E3 | G3: Pet4 | H3: =VLOOKUP(G3,Pets!$B:$E,2,FALSE) | I3: =VLOOKUP(G3,Pets!$B:$E,4,FALSE) | J3: =Assumptions!$B$2 | K3: =I3*60*J3 | L3: 500 | M3: =L3-K3
A4: AppleTreeSeed | B4: Apple Tree Seed | C4: AppleTree | D4: Common | E4: 26 | F4: ="1 in "&E4 | G4: Pet6 | H4: =VLOOKUP(G4,Pets!$B:$E,2,FALSE) | I4: =VLOOKUP(G4,Pets!$B:$E,4,FALSE) | J4: =Assumptions!$B$2 | K4: =I4*60*J4 | L4: 1500 | M4: =L4-K4
A5: PotatoSeed | B5: Potato Seed | C5: PotatoPatch | D5: Rare | E5: 51 | F5: ="1 in "&E5 | G5: Pet9 | H5: =VLOOKUP(G5,Pets!$B:$E,2,FALSE) | I5: =VLOOKUP(G5,Pets!$B:$E,4,FALSE) | J5: =Assumptions!$B$2 | K5: =I5*60*J5 | L5: 2200 | M5: =L5-K5
A6: OrangeTreeSeed | B6: Orange Tree Seed | C6: OrangeTree | D6: Rare | E6: 85 | F6: ="1 in "&E6 | G6: Pet12 | H6: =VLOOKUP(G6,Pets!$B:$E,2,FALSE) | I6: =VLOOKUP(G6,Pets!$B:$E,4,FALSE) | J6: =Assumptions!$B$2 | K6: =I6*60*J6 | L6: 3000 | M6: =L6-K6
A7: WatermelonSeed | B7: Watermelon Seed | C7: WatermelonPatch | D7: Rare | E7: 128 | F7: ="1 in "&E7 | G7: Pet15 | H7: =VLOOKUP(G7,Pets!$B:$E,2,FALSE) | I7: =VLOOKUP(G7,Pets!$B:$E,4,FALSE) | J7: =Assumptions!$B$2 | K7: =I7*60*J7 | L7: 4500 | M7: =L7-K7
A8: PlumTreeSeed | B8: Plum Tree Seed | C8: PlumTree | D8: Rare | E8: 256 | F8: ="1 in "&E8 | G8: Pet17 | H8: =VLOOKUP(G8,Pets!$B:$E,2,FALSE) | I8: =VLOOKUP(G8,Pets!$B:$E,4,FALSE) | J8: =Assumptions!$B$2 | K8: =I8*60*J8 | L8: 5500 | M8: =L8-K8
A9: CornSeed | B9: Corn Seed | C9: CornPatch | D9: Epic | E9: 427 | F9: ="1 in "&E9 | G9: Pet20 | H9: =VLOOKUP(G9,Pets!$B:$E,2,FALSE) | I9: =VLOOKUP(G9,Pets!$B:$E,4,FALSE) | J9: =Assumptions!$B$2 | K9: =I9*60*J9 | L9: 7500 | M9: =L9-K9
A10: CherryTreeSeed | B10: Cherry Tree Seed | C10: CherryTree | D10: Epic | E10: 512 | F10: ="1 in "&E10 | G10: Pet23 | H10: =VLOOKUP(G10,Pets!$B:$E,2,FALSE) | I10: =VLOOKUP(G10,Pets!$B:$E,4,FALSE) | J10: =Assumptions!$B$2 | K10: =I10*60*J10 | L10: 12000 | M10: =L10-K10
A11: MushroomSeed | B11: Mushroom Seed | C11: MushroomPatch | D11: Epic | E11: 640 | F11: ="1 in "&E11 | G11: Pet26 | H11: =VLOOKUP(G11,Pets!$B:$E,2,FALSE) | I11: =VLOOKUP(G11,Pets!$B:$E,4,FALSE) | J11: =Assumptions!$B$2 | K11: =I11*60*J11 | L11: 16000 | M11: =L11-K11
A12: BananaTreeSeed | B12: Banana Tree Seed | C12: BananaTree | D12: Epic | E12: 853 | F12: ="1 in "&E12 | G12: Pet28 | H12: =VLOOKUP(G12,Pets!$B:$E,2,FALSE) | I12: =VLOOKUP(G12,Pets!$B:$E,4,FALSE) | J12: =Assumptions!$B$2 | K12: =I12*60*J12 | L12: 20000 | M12: =L12-K12
A13: CactusSeed | B13: Cactus Seed | C13: Cactus | D13: Epic | E13: 1200 | F13: ="1 in "&E13 | G13: Pet31 | H13: =VLOOKUP(G13,Pets!$B:$E,2,FALSE) | I13: =VLOOKUP(G13,Pets!$B:$E,4,FALSE) | J13: =Assumptions!$B$2 | K13: =I13*60*J13 | L13: 28000 | M13: =L13-K13
... A21: DurianTreeSeed | B21: Durian Tree Seed | C21: DurianTree | D21: Secret | E21: 5120000 | F21: ="1 in "&E21 | G21: Pet53 | H21: =VLOOKUP(G21,Pets!$B:$E,2,FALSE) | I21: =VLOOKUP(G21,Pets!$B:$E,4,FALSE) | J21: =Assumptions!$B$2 | K21: =I21*60*J21 | L21: 180000 | M21: =L21-K21

Sheet LuckUpgrades
A1: Level | B1: LuckPercent | C1: RawFormulaPrice | D1: CurrentPrice | E1: CumulativePrice | F1: CumulativeHoursAtEndgame
A2: 1 | B2: =A2*5 | C2: =Assumptions!$B$6*A2^2*(1+Assumptions!$B$7*(A2/100)^Assumptions!$B$8) | D2: 100 | E2: =SUM($D$2:D2) | F2: =E2/Assumptions!$B$5/3600
A3: 2 | B3: =A3*5 | C3: =Assumptions!$B$6*A3^2*(1+Assumptions!$B$7*(A3/100)^Assumptions!$B$8) | D3: 150 | E3: =SUM($D$2:D3) | F3: =E3/Assumptions!$B$5/3600
A4: 3 | B4: =A4*5 | C4: =Assumptions!$B$6*A4^2*(1+Assumptions!$B$7*(A4/100)^Assumptions!$B$8) | D4: 300 | E4: =SUM($D$2:D4) | F4: =E4/Assumptions!$B$5/3600
A5: 4 | B5: =A5*5 | C5: =Assumptions!$B$6*A5^2*(1+Assumptions!$B$7*(A5/100)^Assumptions!$B$8) | D5: 550 | E5: =SUM($D$2:D5) | F5: =E5/Assumptions!$B$5/3600
A6: 5 | B6: =A6*5 | C6: =Assumptions!$B$6*A6^2*(1+Assumptions!$B$7*(A6/100)^Assumptions!$B$8) | D6: 900 | E6: =SUM($D$2:D6) | F6: =E6/Assumptions!$B$5/3600
A7: 6 | B7: =A7*5 | C7: =Assumptions!$B$6*A7^2*(1+Assumptions!$B$7*(A7/100)^Assumptions!$B$8) | D7: 1250 | E7: =SUM($D$2:D7) | F7: =E7/Assumptions!$B$5/3600
A8: 7 | B8: =A8*5 | C8: =Assumptions!$B$6*A8^2*(1+Assumptions!$B$7*(A8/100)^Assumptions!$B$8) | D8: 1750 | E8: =SUM($D$2:D8) | F8: =E8/Assumptions!$B$5/3600
A9: 8 | B9: =A9*5 | C9: =Assumptions!$B$6*A9^2*(1+Assumptions!$B$7*(A9/100)^Assumptions!$B$8) | D9: 2250 | E9: =SUM($D$2:D9) | F9: =E9/Assumptions!$B$5/3600
A10: 9 | B10: =A10*5 | C10: =Assumptions!$B$6*A10^2*(1+Assumptions!$B$7*(A10/100)^Assumptions!$B$8) | D10: 2750 | E10: =SUM($D$2:D10) | F10: =E10/Assumptions!$B$5/3600
A11: 10 | B11: =A11*5 | C11: =Assumptions!$B$6*A11^2*(1+Assumptions!$B$7*(A11/100)^Assumptions!$B$8) | D11: 3500 | E11: =SUM($D$2:D11) | F11: =E11/Assumptions!$B$5/3600
A12: 11 | B12: =A12*5 | C12: =Assumptions!$B$6*A12^2*(1+Assumptions!$B$7*(A12/100)^Assumptions!$B$8) | D12: 4250 | E12: =SUM($D$2:D12) | F12: =E12/Assumptions!$B$5/3600
A13: 12 | B13: =A13*5 | C13: =Assumptions!$B$6*A13^2*(1+Assumptions!$B$7*(A13/100)^Assumptions!$B$8) | D13: 5000 | E13: =SUM($D$2:D13) | F13: =E13/Assumptions!$B$5/3600
... A101: 100 | B101: =A101*5 | C101: =Assumptions!$B$6*A101^2*(1+Assumptions!$B$7*(A101/100)^Assumptions!$B$8) | D101: 6000000 | E101: =SUM($D$2:D101) | F101: =E101/Assumptions!$B$5/3600

Sheet RollPads
A1: UpgradeLevel | B1: UnlockedPads | C1: Price | D1: CumulativePrice
A2: 1 | B2: 2/5 | C2: 10000 | D2: =SUM($C$2:C2)
A3: 2 | B3: 3/5 | C3: 150000 | D3: =SUM($C$2:C3)
A4: 3 | B4: 4/5 | C4: 1000000 | D4: =SUM($C$2:C4)
A5: 4 | B5: 5/5 | C5: 5000000 | D5: =SUM($C$2:C5)

Sheet Rebirths
A1: RebirthTier | B1: CurrentCost | C1: AnchorPetCount | D1: AnchorPetName | E1: AnchorPetEarnRate | F1: HoursRequired | G1: FormulaCost | H1: CostDelta
A2: 1 | B2: 100000 | C2: 1 | D2: GoldenRetriver | E2: 24 | F2: 1 | G2: =C2*E2*F2*3600 | H2: =B2-G2
A3: 2 | B3: 500000 | C3: 2 | D3: Lizard | E3: 40 | F3: 2 | G3: =C3*E3*F3*3600 | H3: =B3-G3
A4: 3 | B4: 5000000 | C4: 3 | D4: Ostrich | E4: 113 | F4: 4 | G4: =C4*E4*F4*3600 | H4: =B4-G4
A5: 4 | B5: 20000000 | C5: 4 | D5: Gorilla | E5: 228 | F5: 6 | G5: =C5*E5*F5*3600 | H5: =B5-G5
A6: 5 | B6: 50000000 | C6: 5 | D6: Snake | E6: 395 | F6: 8 | G6: =C6*E6*F6*3600 | H6: =B6-G6
A7: 6 | B7: 200000000 | C7: 6 | D7: T-Rex | E7: 800 | F7: 10 | G7: =C7*E7*F7*3600 | H7: =B7-G7
