Workbook

Sheet README
A1: Grid Parts Balance Workbook
A2: Purpose | B2: Balance plot GridPart unlock prices using actual Studio grid coordinates.
A3: How to use | B3: Edit CurrentPrice in RowStages or per-cell CurrentPrice in GridPricing. PlotMap reads the current prices for a visual reference.
A4: Final row rule | B4: Grid numbers 46-50 are the furthest row from StarterPlot and each cost 5 hours at 6x T-Rex earnings.
A5: Implementation note | B5: This workbook is a balance/export artifact. It does not apply Studio UnlockPrice attributes by itself.

Sheet Assumptions
A1: Key | B1: Value | C1: Description
A2: T-RexEarnRate | B2: 800 | C2: T-Rex pet MoneyRate per second from the current pet balance.
A3: FinalRebirthMultiplier | B3: 6 | C3: Final row target assumes 6x T-Rex earnings.
A4: FinalIncomePerSecond | B4: =B2*B3 | C4: 6x T-Rex earnings per second.
A5: FinalHoursPerCell | B5: 5 | C5: Requested final-row cost per grid cell.
A6: FinalRowPricePerCell | B6: =B4*B5*3600 | C6: Final 5 cells should each equal this.

Sheet RowStages
A1: GridZ | B1: Stage | C1: AnchorIncomeSource | D1: IncomePerSecond | E1: TargetHoursPerCell | F1: TargetMinutesPerCell | G1: FormulaPrice | H1: RoundTo | I1: SuggestedRoundedPrice | J1: CurrentPrice | K1: Notes
A2: 1 | B2: Starter expansion | C2: Pet10 Goat | D2: 14 | E2: 0.016666667 | F2: =E2*60 | G2: =D2*E2*3600 | H2: 100 | I2: =ROUND(G2/H2,0)*H2 | J2: 1000
A3: 2 | B3: Rebirth 1 prep | C3: 1x GoldenRetriver | D3: 24 | E3: 0.083333333 | F3: =E3*60 | G3: =D3*E3*3600 | H3: 500 | I3: =ROUND(G3/H3,0)*H3 | J3: 10000
A4: 3 | B4: Rebirth 2 prep | C4: 2x Lizard | D4: 80 | E4: 0.16666667 | F4: =E4*60 | G4: =D4*E4*3600 | H4: 1000 | I4: =ROUND(G4/H4,0)*H4 | J4: 50000
A5: 4 | B5: Rebirth 3 prep | C5: 3x Ostrich | D5: 339 | E5: 0.25 | F5: =E5*60 | G5: =D5*E5*3600 | H5: 5000 | I5: =ROUND(G5/H5,0)*H5 | J5: 300000
A6: 5 | B6: Rebirth 4 prep | C6: 4x Gorilla | D6: 912 | E6: 0.33333333 | F6: =E6*60 | G6: =D6*E6*3600 | H6: 10000 | I6: =ROUND(G6/H6,0)*H6 | J6: 1000000
A7: 6 | B7: Rebirth 5 prep | C7: 5x Snake | D7: 1975 | E7: 0.5 | F7: =E7*60 | G7: =D7*E7*3600 | H7: 50000 | I7: =ROUND(G7/H7,0)*H7 | J7: 3500000
A8: 7 | B8: Rebirth 6 ramp | C8: 6x T-Rex | D8: 4800 | E8: 0.75 | F8: =E8*60 | G8: =D8*E8*3600 | H8: 100000 | I8: =ROUND(G8/H8,0)*H8 | J8: 13000000
A9: 8 | B9: Rebirth 6 ramp | C9: 6x T-Rex | D9: 4800 | E9: 1.5 | F9: =E9*60 | G9: =D9*E9*3600 | H9: 100000 | I9: =ROUND(G9/H9,0)*H9 | J9: 26000000
A10: 9 | B10: Rebirth 6 endgame | C10: 6x T-Rex | D10: 4800 | E10: 2.5 | F10: =E10*60 | G10: =D10*E10*3600 | H10: 100000 | I10: =ROUND(G10/H10,0)*H10 | J10: 43200000
A11: 10 | B11: Final row | C11: 6x T-Rex | D11: 4800 | E11: 5 | F11: =E11*60 | G11: =D11*E11*3600 | H11: 100000 | I11: =ROUND(G11/H11,0)*H11 | J11: 86400000 | K11: Final 5 cells: exact 5h at 6x T-Rex

Sheet GridPricing
A1: GridNo | B1: GridX | C1: GridZ | D1: CoordKey | E1: Type | F1: DistanceRowsFromStarter | G1: Stage | H1: AnchorIncomeSource | I1: IncomePerSecond | J1: TargetHours | K1: FormulaPrice | L1: RoundTo | M1: RowSuggestedPrice | N1: CurrentPrice | O1: ExistingStudioPrice | P1: Notes
A2: 1 | B2: 1 | C2: 1 | D2: 1:1 | E2: Unlockable | F2: =C2-1 | G2: =VLOOKUP(C2,RowStages!$A:$J,2,FALSE) | H2: =VLOOKUP(C2,RowStages!$A:$J,3,FALSE) | I2: =VLOOKUP(C2,RowStages!$A:$J,4,FALSE) | J2: =VLOOKUP(C2,RowStages!$A:$J,5,FALSE) | K2: =IF(E2="Starter",0,I2*J2*3600) | L2: =VLOOKUP(C2,RowStages!$A:$J,8,FALSE) | M2: =IF(E2="Starter",0,ROUND(K2/L2,0)*L2) | N2: 1000 | O2: 3
A3: 2 | B3: 2 | C3: 1 | D3: 2:1 | E3: Unlockable | F3: =C3-1 | G3: =VLOOKUP(C3,RowStages!$A:$J,2,FALSE) | H3: =VLOOKUP(C3,RowStages!$A:$J,3,FALSE) | I3: =VLOOKUP(C3,RowStages!$A:$J,4,FALSE) | J3: =VLOOKUP(C3,RowStages!$A:$J,5,FALSE) | K3: =IF(E3="Starter",0,I3*J3*3600) | L3: =VLOOKUP(C3,RowStages!$A:$J,8,FALSE) | M3: =IF(E3="Starter",0,ROUND(K3/L3,0)*L3) | N3: 100 | O3: 100
A4: 3 | B4: 3 | C4: 1 | D4: 3:1 | E4: Starter | F4: =C4-1 | G4: =VLOOKUP(C4,RowStages!$A:$J,2,FALSE) | H4: =VLOOKUP(C4,RowStages!$A:$J,3,FALSE) | I4: =VLOOKUP(C4,RowStages!$A:$J,4,FALSE) | J4: =VLOOKUP(C4,RowStages!$A:$J,5,FALSE) | K4: =IF(E4="Starter",0,I4*J4*3600) | L4: =VLOOKUP(C4,RowStages!$A:$J,8,FALSE) | M4: =IF(E4="Starter",0,ROUND(K4/L4,0)*L4) | N4: 0 | O4: 0 | P4: StarterPlot
A5: 4 | B5: 4 | C5: 1 | D5: 4:1 | E5: Unlockable | F5: =C5-1 | G5: =VLOOKUP(C5,RowStages!$A:$J,2,FALSE) | H5: =VLOOKUP(C5,RowStages!$A:$J,3,FALSE) | I5: =VLOOKUP(C5,RowStages!$A:$J,4,FALSE) | J5: =VLOOKUP(C5,RowStages!$A:$J,5,FALSE) | K5: =IF(E5="Starter",0,I5*J5*3600) | L5: =VLOOKUP(C5,RowStages!$A:$J,8,FALSE) | M5: =IF(E5="Starter",0,ROUND(K5/L5,0)*L5) | N5: 1000 | O5: 3
A6: 5 | B6: 5 | C6: 1 | D6: 5:1 | E6: Unlockable | F6: =C6-1 | G6: =VLOOKUP(C6,RowStages!$A:$J,2,FALSE) | H6: =VLOOKUP(C6,RowStages!$A:$J,3,FALSE) | I6: =VLOOKUP(C6,RowStages!$A:$J,4,FALSE) | J6: =VLOOKUP(C6,RowStages!$A:$J,5,FALSE) | K6: =IF(E6="Starter",0,I6*J6*3600) | L6: =VLOOKUP(C6,RowStages!$A:$J,8,FALSE) | M6: =IF(E6="Starter",0,ROUND(K6/L6,0)*L6) | N6: 1000 | O6: 3
A7: 6 | B7: 1 | C7: 2 | D7: 1:2 | E7: Unlockable | F7: =C7-1 | G7: =VLOOKUP(C7,RowStages!$A:$J,2,FALSE) | H7: =VLOOKUP(C7,RowStages!$A:$J,3,FALSE) | I7: =VLOOKUP(C7,RowStages!$A:$J,4,FALSE) | J7: =VLOOKUP(C7,RowStages!$A:$J,5,FALSE) | K7: =IF(E7="Starter",0,I7*J7*3600) | L7: =VLOOKUP(C7,RowStages!$A:$J,8,FALSE) | M7: =IF(E7="Starter",0,ROUND(K7/L7,0)*L7) | N7: 10000 | O7: 3
A8: 7 | B8: 2 | C8: 2 | D8: 2:2 | E8: Unlockable | F8: =C8-1 | G8: =VLOOKUP(C8,RowStages!$A:$J,2,FALSE) | H8: =VLOOKUP(C8,RowStages!$A:$J,3,FALSE) | I8: =VLOOKUP(C8,RowStages!$A:$J,4,FALSE) | J8: =VLOOKUP(C8,RowStages!$A:$J,5,FALSE) | K8: =IF(E8="Starter",0,I8*J8*3600) | L8: =VLOOKUP(C8,RowStages!$A:$J,8,FALSE) | M8: =IF(E8="Starter",0,ROUND(K8/L8,0)*L8) | N8: 10000 | O8: 3
A9: 8 | B9: 3 | C9: 2 | D9: 3:2 | E9: Unlockable | F9: =C9-1 | G9: =VLOOKUP(C9,RowStages!$A:$J,2,FALSE) | H9: =VLOOKUP(C9,RowStages!$A:$J,3,FALSE) | I9: =VLOOKUP(C9,RowStages!$A:$J,4,FALSE) | J9: =VLOOKUP(C9,RowStages!$A:$J,5,FALSE) | K9: =IF(E9="Starter",0,I9*J9*3600) | L9: =VLOOKUP(C9,RowStages!$A:$J,8,FALSE) | M9: =IF(E9="Starter",0,ROUND(K9/L9,0)*L9) | N9: 10000 | O9: 3
A10: 9 | B10: 4 | C10: 2 | D10: 4:2 | E10: Unlockable | F10: =C10-1 | G10: =VLOOKUP(C10,RowStages!$A:$J,2,FALSE) | H10: =VLOOKUP(C10,RowStages!$A:$J,3,FALSE) | I10: =VLOOKUP(C10,RowStages!$A:$J,4,FALSE) | J10: =VLOOKUP(C10,RowStages!$A:$J,5,FALSE) | K10: =IF(E10="Starter",0,I10*J10*3600) | L10: =VLOOKUP(C10,RowStages!$A:$J,8,FALSE) | M10: =IF(E10="Starter",0,ROUND(K10/L10,0)*L10) | N10: 10000 | O10: 3
A11: 10 | B11: 5 | C11: 2 | D11: 5:2 | E11: Unlockable | F11: =C11-1 | G11: =VLOOKUP(C11,RowStages!$A:$J,2,FALSE) | H11: =VLOOKUP(C11,RowStages!$A:$J,3,FALSE) | I11: =VLOOKUP(C11,RowStages!$A:$J,4,FALSE) | J11: =VLOOKUP(C11,RowStages!$A:$J,5,FALSE) | K11: =IF(E11="Starter",0,I11*J11*3600) | L11: =VLOOKUP(C11,RowStages!$A:$J,8,FALSE) | M11: =IF(E11="Starter",0,ROUND(K11/L11,0)*L11) | N11: 10000 | O11: 3
A12: 11 | B12: 1 | C12: 3 | D12: 1:3 | E12: Unlockable | F12: =C12-1 | G12: =VLOOKUP(C12,RowStages!$A:$J,2,FALSE) | H12: =VLOOKUP(C12,RowStages!$A:$J,3,FALSE) | I12: =VLOOKUP(C12,RowStages!$A:$J,4,FALSE) | J12: =VLOOKUP(C12,RowStages!$A:$J,5,FALSE) | K12: =IF(E12="Starter",0,I12*J12*3600) | L12: =VLOOKUP(C12,RowStages!$A:$J,8,FALSE) | M12: =IF(E12="Starter",0,ROUND(K12/L12,0)*L12) | N12: 50000 | O12: 3
A13: 12 | B13: 2 | C13: 3 | D13: 2:3 | E13: Unlockable | F13: =C13-1 | G13: =VLOOKUP(C13,RowStages!$A:$J,2,FALSE) | H13: =VLOOKUP(C13,RowStages!$A:$J,3,FALSE) | I13: =VLOOKUP(C13,RowStages!$A:$J,4,FALSE) | J13: =VLOOKUP(C13,RowStages!$A:$J,5,FALSE) | K13: =IF(E13="Starter",0,I13*J13*3600) | L13: =VLOOKUP(C13,RowStages!$A:$J,8,FALSE) | M13: =IF(E13="Starter",0,ROUND(K13/L13,0)*L13) | N13: 50000 | O13: 3
A14: 13 | B14: 3 | C14: 3 | D14: 3:3 | E14: Unlockable | F14: =C14-1 | G14: =VLOOKUP(C14,RowStages!$A:$J,2,FALSE) | H14: =VLOOKUP(C14,RowStages!$A:$J,3,FALSE) | I14: =VLOOKUP(C14,RowStages!$A:$J,4,FALSE) | J14: =VLOOKUP(C14,RowStages!$A:$J,5,FALSE) | K14: =IF(E14="Starter",0,I14*J14*3600) | L14: =VLOOKUP(C14,RowStages!$A:$J,8,FALSE) | M14: =IF(E14="Starter",0,ROUND(K14/L14,0)*L14) | N14: 50000 | O14: 3
A15: 14 | B15: 4 | C15: 3 | D15: 4:3 | E15: Unlockable | F15: =C15-1 | G15: =VLOOKUP(C15,RowStages!$A:$J,2,FALSE) | H15: =VLOOKUP(C15,RowStages!$A:$J,3,FALSE) | I15: =VLOOKUP(C15,RowStages!$A:$J,4,FALSE) | J15: =VLOOKUP(C15,RowStages!$A:$J,5,FALSE) | K15: =IF(E15="Starter",0,I15*J15*3600) | L15: =VLOOKUP(C15,RowStages!$A:$J,8,FALSE) | M15: =IF(E15="Starter",0,ROUND(K15/L15,0)*L15) | N15: 50000 | O15: 3
A16: 15 | B16: 5 | C16: 3 | D16: 5:3 | E16: Unlockable | F16: =C16-1 | G16: =VLOOKUP(C16,RowStages!$A:$J,2,FALSE) | H16: =VLOOKUP(C16,RowStages!$A:$J,3,FALSE) | I16: =VLOOKUP(C16,RowStages!$A:$J,4,FALSE) | J16: =VLOOKUP(C16,RowStages!$A:$J,5,FALSE) | K16: =IF(E16="Starter",0,I16*J16*3600) | L16: =VLOOKUP(C16,RowStages!$A:$J,8,FALSE) | M16: =IF(E16="Starter",0,ROUND(K16/L16,0)*L16) | N16: 50000 | O16: 3
... A46: 45 | B46: 5 | C46: 9 | D46: 5:9 | E46: Unlockable | F46: =C46-1 | G46: =VLOOKUP(C46,RowStages!$A:$J,2,FALSE) | H46: =VLOOKUP(C46,RowStages!$A:$J,3,FALSE) | I46: =VLOOKUP(C46,RowStages!$A:$J,4,FALSE) | J46: =VLOOKUP(C46,RowStages!$A:$J,5,FALSE) | K46: =IF(E46="Starter",0,I46*J46*3600) | L46: =VLOOKUP(C46,RowStages!$A:$J,8,FALSE) | M46: =IF(E46="Starter",0,ROUND(K46/L46,0)*L46) | N46: 43200000 | O46: 3
A47: 46 | B47: 1 | C47: 10 | D47: 1:10 | E47: Unlockable | F47: =C47-1 | G47: =VLOOKUP(C47,RowStages!$A:$J,2,FALSE) | H47: =VLOOKUP(C47,RowStages!$A:$J,3,FALSE) | I47: =VLOOKUP(C47,RowStages!$A:$J,4,FALSE) | J47: =VLOOKUP(C47,RowStages!$A:$J,5,FALSE) | K47: =IF(E47="Starter",0,I47*J47*3600) | L47: =VLOOKUP(C47,RowStages!$A:$J,8,FALSE) | M47: =IF(E47="Starter",0,ROUND(K47/L47,0)*L47) | N47: 86400000 | O47: 3 | P47: Final 5: 5h at 6x T-Rex
A48: 47 | B48: 2 | C48: 10 | D48: 2:10 | E48: Unlockable | F48: =C48-1 | G48: =VLOOKUP(C48,RowStages!$A:$J,2,FALSE) | H48: =VLOOKUP(C48,RowStages!$A:$J,3,FALSE) | I48: =VLOOKUP(C48,RowStages!$A:$J,4,FALSE) | J48: =VLOOKUP(C48,RowStages!$A:$J,5,FALSE) | K48: =IF(E48="Starter",0,I48*J48*3600) | L48: =VLOOKUP(C48,RowStages!$A:$J,8,FALSE) | M48: =IF(E48="Starter",0,ROUND(K48/L48,0)*L48) | N48: 86400000 | O48: 3 | P48: Final 5: 5h at 6x T-Rex
A49: 48 | B49: 3 | C49: 10 | D49: 3:10 | E49: Unlockable | F49: =C49-1 | G49: =VLOOKUP(C49,RowStages!$A:$J,2,FALSE) | H49: =VLOOKUP(C49,RowStages!$A:$J,3,FALSE) | I49: =VLOOKUP(C49,RowStages!$A:$J,4,FALSE) | J49: =VLOOKUP(C49,RowStages!$A:$J,5,FALSE) | K49: =IF(E49="Starter",0,I49*J49*3600) | L49: =VLOOKUP(C49,RowStages!$A:$J,8,FALSE) | M49: =IF(E49="Starter",0,ROUND(K49/L49,0)*L49) | N49: 86400000 | O49: 3 | P49: Final 5: 5h at 6x T-Rex
A50: 49 | B50: 4 | C50: 10 | D50: 4:10 | E50: Unlockable | F50: =C50-1 | G50: =VLOOKUP(C50,RowStages!$A:$J,2,FALSE) | H50: =VLOOKUP(C50,RowStages!$A:$J,3,FALSE) | I50: =VLOOKUP(C50,RowStages!$A:$J,4,FALSE) | J50: =VLOOKUP(C50,RowStages!$A:$J,5,FALSE) | K50: =IF(E50="Starter",0,I50*J50*3600) | L50: =VLOOKUP(C50,RowStages!$A:$J,8,FALSE) | M50: =IF(E50="Starter",0,ROUND(K50/L50,0)*L50) | N50: 86400000 | O50: 3 | P50: Final 5: 5h at 6x T-Rex
A51: 50 | B51: 5 | C51: 10 | D51: 5:10 | E51: Unlockable | F51: =C51-1 | G51: =VLOOKUP(C51,RowStages!$A:$J,2,FALSE) | H51: =VLOOKUP(C51,RowStages!$A:$J,3,FALSE) | I51: =VLOOKUP(C51,RowStages!$A:$J,4,FALSE) | J51: =VLOOKUP(C51,RowStages!$A:$J,5,FALSE) | K51: =IF(E51="Starter",0,I51*J51*3600) | L51: =VLOOKUP(C51,RowStages!$A:$J,8,FALSE) | M51: =IF(E51="Starter",0,ROUND(K51/L51,0)*L51) | N51: 86400000 | O51: 3 | P51: Final 5: 5h at 6x T-Rex

Sheet PlotMap
B1: GridX 1 | C1: GridX 2 | D1: GridX 3 | E1: GridX 4 | F1: GridX 5
A2: GridZ 10 | B2: Grid 46 X1 Z10 $86,400,000 | C2: Grid 47 X2 Z10 $86,400,000 | D2: Grid 48 X3 Z10 $86,400,000 | E2: Grid 49 X4 Z10 $86,400,000 | F2: Grid 50 X5 Z10 $86,400,000
A3: GridZ 9 | B3: Grid 41 X1 Z9 $43,200,000 | C3: Grid 42 X2 Z9 $43,200,000 | D3: Grid 43 X3 Z9 $43,200,000 | E3: Grid 44 X4 Z9 $43,200,000 | F3: Grid 45 X5 Z9 $43,200,000
A4: GridZ 8 | B4: Grid 36 X1 Z8 $26,000,000 | C4: Grid 37 X2 Z8 $26,000,000 | D4: Grid 38 X3 Z8 $26,000,000 | E4: Grid 39 X4 Z8 $26,000,000 | F4: Grid 40 X5 Z8 $26,000,000
A5: GridZ 7 | B5: Grid 31 X1 Z7 $13,000,000 | C5: Grid 32 X2 Z7 $13,000,000 | D5: Grid 33 X3 Z7 $13,000,000 | E5: Grid 34 X4 Z7 $13,000,000 | F5: Grid 35 X5 Z7 $13,000,000
A6: GridZ 6 | B6: Grid 26 X1 Z6 $3,500,000 | C6: Grid 27 X2 Z6 $3,500,000 | D6: Grid 28 X3 Z6 $3,500,000 | E6: Grid 29 X4 Z6 $3,500,000 | F6: Grid 30 X5 Z6 $3,500,000
A7: GridZ 5 | B7: Grid 21 X1 Z5 $1,000,000 | C7: Grid 22 X2 Z5 $1,000,000 | D7: Grid 23 X3 Z5 $1,000,000 | E7: Grid 24 X4 Z5 $1,000,000 | F7: Grid 25 X5 Z5 $1,000,000
A8: GridZ 4 | B8: Grid 16 X1 Z4 $300,000 | C8: Grid 17 X2 Z4 $300,000 | D8: Grid 18 X3 Z4 $300,000 | E8: Grid 19 X4 Z4 $300,000 | F8: Grid 20 X5 Z4 $300,000
A9: GridZ 3 | B9: Grid 11 X1 Z3 $50,000 | C9: Grid 12 X2 Z3 $50,000 | D9: Grid 13 X3 Z3 $50,000 | E9: Grid 14 X4 Z3 $50,000 | F9: Grid 15 X5 Z3 $50,000
A10: GridZ 2 | B10: Grid 6 X1 Z2 $10,000 | C10: Grid 7 X2 Z2 $10,000 | D10: Grid 8 X3 Z2 $10,000 | E10: Grid 9 X4 Z2 $10,000 | F10: Grid 10 X5 Z2 $10,000
A11: GridZ 1 | B11: Grid 1 X1 Z1 $1,000 | C11: Grid 2 X2 Z1 $100 | D11: Grid 3 X3 Z1 STARTER | E11: Grid 4 X4 Z1 $1,000 | F11: Grid 5 X5 Z1 $1,000

Sheet RebirthAnchors
A1: Tier | B1: Cost | C1: AnchorFormula | D1: Notes
A2: 1 | B2: 100000 | C2: 1x GoldenRetriever, 1h | D2: Existing rebirth cost anchor
A3: 2 | B3: 500000 | C3: 2x Lizard, 2h | D3: Existing rebirth cost anchor
A4: 3 | B4: 5000000 | C4: 3x Ostrich, 4h | D4: Existing rebirth cost anchor
A5: 4 | B5: 20000000 | C5: 4x Gorilla, 6h | D5: Existing rebirth cost anchor
A6: 5 | B6: 50000000 | C6: 5x Snake, 8h | D6: Existing rebirth cost anchor
A7: 6 | B7: 200000000 | C7: 6x T-Rex, 10h | D7: Existing rebirth cost anchor
